asuswrtspeedtest/__init__.py
asuswrtspeedtest/speedtest_client.py
asuswrtspeedtest-0.2.1.dist-info/METADATA
asuswrtspeedtest-0.2.1.dist-info/WHEEL
asuswrtspeedtest-0.2.1.dist-info/licenses/LICENSE
asuswrtspeedtest-0.2.1.dist-info/RECORD
