Metadata-Version: 2.4
Name: asuswrtspeedtest
Version: 0.2.1
Summary: Programatically run internet speedtests on your AsusWRT-powered routers
Project-URL: Homepage, https://github.com/mdinicola/python-asuswrt-speedtest
Author-email: Mike Di Nicola <mike@mdinicola.com>
License-File: LICENSE
Classifier: Development Status :: 4 - Beta
Classifier: Intended Audience :: Developers
Classifier: License :: OSI Approved :: MIT License
Classifier: Operating System :: OS Independent
Classifier: Programming Language :: Python :: 3
Requires-Python: >=3.8
Requires-Dist: pyasuswrt
Provides-Extra: lint
Requires-Dist: flake8; extra == 'lint'
Provides-Extra: test
Requires-Dist: pytest; extra == 'test'
Requires-Dist: pytest-asyncio; extra == 'test'
